charrnn/__init__.py
charrnn/__main__.py
charrnn/cli.py
charrnn/const.py
charrnn/decoder.py
charrnn/model.py
charrnn/text.py
charrnn/train.py
charrnn/version.py
charrnn-0.1.1.dist-info/DESCRIPTION.rst
charrnn-0.1.1.dist-info/LICENSE.txt
charrnn-0.1.1.dist-info/METADATA
charrnn-0.1.1.dist-info/RECORD
charrnn-0.1.1.dist-info/WHEEL
charrnn-0.1.1.dist-info/entry_points.txt
charrnn-0.1.1.dist-info/metadata.json
charrnn-0.1.1.dist-info/top_level.txt
