Metadata-Version: 2.0
Name: charrnn
Version: 0.1.1
Summary: Character Recurrent Neural Network For Text Generation
Home-page: https://github.com/jjangsangy/Word2Seq
Author: Sang Han
Author-email: sanghan@protonmail.com
License: Apache License 2.0
Platform: UNKNOWN
Classifier: Development Status :: 5 - Production/Stable
Classifier: Environment :: Console
Classifier: Intended Audience :: Developers
Classifier: Natural Language :: English
Classifier: License :: OSI Approved :: Apache Software License
Classifier: Operating System :: OS Independent
Classifier: Programming Language :: Unix Shell
Classifier: Programming Language :: Python
Classifier: Programming Language :: Python :: 3.6
Classifier: Topic :: Software Development :: Libraries :: Python Modules
Classifier: Topic :: Text Processing :: Linguistic
Classifier: Topic :: Utilities
Requires-Dist: h5py (==2.7.1)
Requires-Dist: Keras (==2.0.9)
Requires-Dist: tensorflow (==1.4.0rc0)
Requires-Dist: future
